ezdict/__init__.py
ezdict/ezdict.py
ezdict-1.0.0.dist-info/LICENSE
ezdict-1.0.0.dist-info/METADATA
ezdict-1.0.0.dist-info/WHEEL
ezdict-1.0.0.dist-info/top_level.txt
ezdict-1.0.0.dist-info/RECORD
