Metadata-Version: 2.1
Name: ezdict
Version: 1.0.0
Summary: Making Python's `dict` easier to work with by adding object notation and grouping
Home-page: https://github.com/BlendingJake/EZDict
Author: Jacob Morris
Author-email: blendingjake@gmail.com
License: UNKNOWN
Platform: UNKNOWN
Classifier: Programming Language :: Python :: 3
Classifier: License :: OSI Approved :: GNU General Public License v3 (GPLv3)
Classifier: Operating System :: OS Independent
Classifier: Topic :: Utilities
Classifier: Topic :: Software Development :: Libraries
Requires-Python: >=3.5
